baihe_config/__init__.py
baihe_config/base.py
baihe_config-0.1.2.dist-info/METADATA
baihe_config-0.1.2.dist-info/WHEEL
baihe_config-0.1.2.dist-info/RECORD
