Metadata-Version: 2.4
Name: baihe-config
Version: 0.1.2
Summary: 基于 Pydantic 的结构化配置管理工具，支持配置的持久化与自动保存，适用于需要高可靠性和易用性的 Python 应用配置场景。
Author-email: jiangbaihe <baiheqiuhan@qq.com>
Requires-Python: >=3.11
Requires-Dist: pydantic>=2.11.7
